{
  "generatedAt": "2026-02-16T05:36:29.532Z",
  "timeZone": "Asia/Tokyo",
  "hourPath": "2026/02/16/14",
  "source": "http://www.data.jma.go.jp/developer/xml/feed/extra.xml",
  "totalItems": 48,
  "items": [
    {
      "originId": "https://www.data.jma.go.jp/developer/xml/data/20260216040924_0_VPWW53_380000.xml",
      "title": "気象特別警報・警報・注意報",
      "content": "【愛媛県気象警報・注意報】南予では、１６日夜のはじめ頃から１７日昼前まで強風や高波に注意してください。",
      "observedAt": "2026-02-16T04:09:24.000Z",
      "placeCountry": "日本",
      "placePref": "愛媛県",
      "placeCity": null,
      "latitude": 33.6013646,
      "longitude": 132.8185275
    },
    {
      "originId": "https://www.data.jma.go.jp/developer/xml/data/20260216040529_0_VPWW53_140000.xml",
      "title": "気象特別警報・警報・注意報",
      "content": "【神奈川県気象警報・注意報】神奈川県では、１６日夜のはじめ頃から１７日明け方まで強風に注意してください。",
      "observedAt": "2026-02-16T04:05:29.000Z",
      "placeCountry": "日本",
      "placePref": "神奈川県",
      "placeCity": null,
      "latitude": 35.4342935,
      "longitude": 139.374753
    },
    {
      "originId": "https://www.data.jma.go.jp/developer/xml/data/20260216031730_0_VPWW53_210000.xml",
      "title": "気象特別警報・警報・注意報",
      "content": "【岐阜県気象警報・注意報】美濃地方では、１７日まで空気の乾燥した状態が続くため、火の取り扱いに注意してください。岐阜県では、１６日までなだれに注意してください。",
      "observedAt": "2026-02-16T03:17:29.000Z",
      "placeCountry": "日本",
      "placePref": "岐阜県",
      "placeCity": null,
      "latitude": 35.7867449,
      "longitude": 137.0460777
    },
    {
      "originId": "https://www.data.jma.go.jp/developer/xml/data/20260216024033_0_VPWW53_430000.xml",
      "title": "気象特別警報・警報・注意報",
      "content": "【熊本県気象警報・注意報】熊本地方では１６日夕方から１７日明け方まで、天草・芦北地方では１６日夕方から１７日昼前まで、強風に注意してください。",
      "observedAt": "2026-02-16T02:40:32.000Z",
      "placeCountry": "日本",
      "placePref": "熊本県",
      "placeCity": null,
      "latitude": 32.6450475,
      "longitude": 130.6341345
    },
    {
      "originId": "https://www.data.jma.go.jp/developer/xml/data/20260216023136_0_VPWW53_350000.xml",
      "title": "気象特別警報・警報・注意報",
      "content": "【山口県気象警報・注意報】山口県では、強風に注意してください。西部、東部、北部では、高波に注意してください。",
      "observedAt": "2026-02-16T02:31:36.000Z",
      "placeCountry": "日本",
      "placePref": "山口県",
      "placeCity": null,
      "latitude": 34.2379614,
      "longitude": 131.5873845
    },
    {
      "originId": "https://www.data.jma.go.jp/developer/xml/data/20260216022940_0_VPWW53_420000.xml",
      "title": "気象特別警報・警報・注意報",
      "content": "【長崎県気象警報・注意報】壱岐・対馬では１６日夜遅くまで、南部、北部では１７日明け方まで、強風に注意してください。壱岐・対馬では、１６日夕方から１７日明け方まで高波に注意してください。",
      "observedAt": "2026-02-16T02:29:39.000Z",
      "placeCountry": "日本",
      "placePref": "長崎県",
      "placeCity": null,
      "latitude": 33.1154683,
      "longitude": 129.7874339
    },
    {
      "originId": "https://www.data.jma.go.jp/developer/xml/data/20260216020612_0_VPWW53_340000.xml",
      "title": "気象特別警報・警報・注意報",
      "content": "【広島県気象警報・注意報】北部では、１８日までなだれに注意してください。",
      "observedAt": "2026-02-16T02:06:11.000Z",
      "placeCountry": "日本",
      "placePref": "広島県",
      "placeCity": null,
      "latitude": 34.5666725,
      "longitude": 132.753565
    },
    {
      "originId": "https://www.data.jma.go.jp/developer/xml/data/20260216012321_0_VPWW53_410000.xml",
      "title": "気象特別警報・警報・注意報",
      "content": "【佐賀県気象警報・注意報】北部では、１７日明け方まで強風に注意してください。",
      "observedAt": "2026-02-16T01:23:20.000Z",
      "placeCountry": "日本",
      "placePref": "佐賀県",
      "placeCity": null,
      "latitude": 33.2185408,
      "longitude": 130.1296585
    },
    {
      "originId": "https://www.data.jma.go.jp/developer/xml/data/20260216012312_0_VPWW53_440000.xml",
      "title": "気象特別警報・警報・注意報",
      "content": "【大分県気象警報・注意報】南部では、１７日昼前まで強風や高波に注意してください。",
      "observedAt": "2026-02-16T01:23:11.000Z",
      "placeCountry": "日本",
      "placePref": "大分県",
      "placeCity": null,
      "latitude": 33.1819875,
      "longitude": 131.4270217
    },
    {
      "originId": "https://www.data.jma.go.jp/developer/xml/data/20260216012018_0_VPWW53_400000.xml",
      "title": "気象特別警報・警報・注意報",
      "content": "【福岡県気象警報・注意報】福岡、北九州地方では、１６日夜遅くまで強風に、１６日昼過ぎから１７日朝まで高波に注意してください。",
      "observedAt": "2026-02-16T01:20:17.000Z",
      "placeCountry": "日本",
      "placePref": "福岡県",
      "placeCity": null,
      "latitude": 33.6251241,
      "longitude": 130.6180016
    },
    {
      "originId": "https://www.data.jma.go.jp/developer/xml/data/20260216010745_0_VPWW53_230000.xml",
      "title": "気象特別警報・警報・注意報",
      "content": "【愛知県気象警報・注意報】愛知県では、強風と、空気の乾燥した状態が続くため火の取り扱いに注意してください。",
      "observedAt": "2026-02-16T01:07:44.000Z",
      "placeCountry": "日本",
      "placePref": "愛知県",
      "placeCity": null,
      "latitude": 34.9991645,
      "longitude": 137.254574
    },
    {
      "originId": "https://www.data.jma.go.jp/developer/xml/data/20260216010549_0_VPWW53_190000.xml",
      "title": "気象特別警報・警報・注意報",
      "content": "【山梨県気象警報・注意報】注意報を解除します。",
      "observedAt": "2026-02-16T01:05:48.000Z",
      "placeCountry": "日本",
      "placePref": "山梨県",
      "placeCity": null,
      "latitude": 35.6399328,
      "longitude": 138.6380495
    },
    {
      "originId": "https://www.data.jma.go.jp/developer/xml/data/20260216010334_0_VPWW53_220000.xml",
      "title": "気象特別警報・警報・注意報",
      "content": "【静岡県気象警報・注意報】中部、西部では１６日昼過ぎから１７日明け方まで、伊豆では１６日夕方から１７日朝まで、強風に注意してください。",
      "observedAt": "2026-02-16T01:03:33.000Z",
      "placeCountry": "日本",
      "placePref": "静岡県",
      "placeCity": null,
      "latitude": 34.9332488,
      "longitude": 138.0955398
    },
    {
      "originId": "https://www.data.jma.go.jp/developer/xml/data/20260216010321_0_VPWW53_120000.xml",
      "title": "気象特別警報・警報・注意報",
      "content": "【千葉県気象警報・注意報】北東部、南部では、１６日夜のはじめ頃から１７日明け方まで強風に、１６日昼過ぎから１７日昼前まで高波に注意してください。",
      "observedAt": "2026-02-16T01:03:20.000Z",
      "placeCountry": "日本",
      "placePref": "千葉県",
      "placeCity": null,
      "latitude": 35.549399,
      "longitude": 140.2647303
    },
    {
      "originId": "https://www.data.jma.go.jp/developer/xml/data/20260216010317_0_VPWW53_150000.xml",
      "title": "気象特別警報・警報・注意報",
      "content": "【新潟県気象警報・注意報】下越、佐渡では、１６日夜遅くまで高波に注意してください。",
      "observedAt": "2026-02-16T01:03:16.000Z",
      "placeCountry": "日本",
      "placePref": "新潟県",
      "placeCity": null,
      "latitude": 37.6452283,
      "longitude": 138.7669125
    },
    {
      "originId": "https://www.data.jma.go.jp/developer/xml/data/20260216010155_0_VPWW53_080000.xml",
      "title": "気象特別警報・警報・注意報",
      "content": "【茨城県気象警報・注意報】南部では、１６日夜のはじめ頃から１７日明け方まで強風に、１６日昼過ぎから１７日昼前まで高波に注意してください。",
      "observedAt": "2026-02-16T01:01:55.000Z",
      "placeCountry": "日本",
      "placePref": "茨城県",
      "placeCity": null,
      "latitude": 36.2869536,
      "longitude": 140.4703384
    },
    {
      "originId": "https://www.data.jma.go.jp/developer/xml/data/20260216005519_0_VPWW53_110000.xml",
      "title": "気象特別警報・警報・注意報",
      "content": "【埼玉県気象警報・注意報】南部、北部では、１７日明け方まで強風に、１６日まで空気の乾燥した状態が続くため、火の取り扱いに注意してください。",
      "observedAt": "2026-02-16T00:55:18.000Z",
      "placeCountry": "日本",
      "placePref": "埼玉県",
      "placeCity": null,
      "latitude": 35.9754168,
      "longitude": 139.4160114
    },
    {
      "originId": "https://www.data.jma.go.jp/developer/xml/data/20260216005310_0_VPWW53_280000.xml",
      "title": "気象特別警報・警報・注意報",
      "content": "【兵庫県気象警報・注意報】南部では、１６日昼過ぎから１６日夜遅くまで強風や高波に注意してください。兵庫県では、１８日までなだれに注意してください。",
      "observedAt": "2026-02-16T00:53:09.000Z",
      "placeCountry": "日本",
      "placePref": "兵庫県",
      "placeCity": null,
      "latitude": 34.914934,
      "longitude": 134.860666
    },
    {
      "originId": "https://www.data.jma.go.jp/developer/xml/data/20260216004430_0_VPWW53_260000.xml",
      "title": "気象特別警報・警報・注意報",
      "content": "【京都府気象警報・注意報】北部では、１７日までなだれに注意してください。",
      "observedAt": "2026-02-16T00:44:29.000Z",
      "placeCountry": "日本",
      "placePref": "京都府",
      "placeCity": null,
      "latitude": 35.242552,
      "longitude": 135.454601
    },
    {
      "originId": "https://www.data.jma.go.jp/developer/xml/data/20260216004024_0_VPWW53_310000.xml",
      "title": "気象特別警報・警報・注意報",
      "content": "【鳥取県気象警報・注意報】鳥取県では、１６日昼過ぎから１６日夜のはじめ頃まで高波に、１８日までなだれに注意してください。",
      "observedAt": "2026-02-16T00:40:24.000Z",
      "placeCountry": "日本",
      "placePref": "鳥取県",
      "placeCity": null,
      "latitude": 35.3555075,
      "longitude": 133.8678525
    },
    {
      "originId": "https://www.data.jma.go.jp/developer/xml/data/20260216004023_0_VPWW53_320000.xml",
      "title": "気象特別警報・警報・注意報",
      "content": "【島根県気象警報・注意報】島根県では、高波に注意してください。東部では、なだれに注意してください。隠岐では、低温に注意してください。",
      "observedAt": "2026-02-16T00:40:23.000Z",
      "placeCountry": "日本",
      "placePref": "島根県",
      "placeCity": null,
      "latitude": 34.9418212,
      "longitude": 132.537439
    },
    {
      "originId": "https://www.data.jma.go.jp/developer/xml/data/20260216004006_0_VPWW53_460100.xml",
      "title": "気象特別警報・警報・注意報",
      "content": "【鹿児島県（奄美地方を除く）気象警報・注意報】注意報を解除します。",
      "observedAt": "2026-02-16T00:40:05.000Z",
      "placeCountry": "日本",
      "placePref": "鹿児島県",
      "placeCity": null,
      "latitude": 31.521587,
      "longitude": 130.5474077
    },
    {
      "originId": "https://www.data.jma.go.jp/developer/xml/data/20260215235119_0_VPWW53_340000.xml",
      "title": "気象特別警報・警報・注意報",
      "content": "【広島県気象警報・注意報】南部では、１６日昼前まで濃霧による視程障害に注意してください。北部では、１７日までなだれに注意してください。",
      "observedAt": "2026-02-15T23:51:19.000Z",
      "placeCountry": "日本",
      "placePref": "広島県",
      "placeCity": null,
      "latitude": 34.5666725,
      "longitude": 132.753565
    },
    {
      "originId": "https://www.data.jma.go.jp/developer/xml/data/20260215224409_0_VPWW53_200000.xml",
      "title": "気象特別警報・警報・注意報",
      "content": "【長野県気象警報・注意報】中部、南部では、１６日までなだれに注意してください。",
      "observedAt": "2026-02-15T22:44:09.000Z",
      "placeCountry": "日本",
      "placePref": "長野県",
      "placeCity": null,
      "latitude": 36.1143945,
      "longitude": 138.0319015
    },
    {
      "originId": "https://www.data.jma.go.jp/developer/xml/data/20260215223734_0_VPWW53_190000.xml",
      "title": "気象特別警報・警報・注意報",
      "content": "【山梨県気象警報・注意報】中・西部では、１６日昼前まで濃霧による視程障害に注意してください。",
      "observedAt": "2026-02-15T22:37:34.000Z",
      "placeCountry": "日本",
      "placePref": "山梨県",
      "placeCity": null,
      "latitude": 35.6399328,
      "longitude": 138.6380495
    },
    {
      "originId": "https://www.data.jma.go.jp/developer/xml/data/20260215222340_0_VPWW53_390000.xml",
      "title": "気象特別警報・警報・注意報",
      "content": "【高知県気象警報・注意報】中部では１６日昼過ぎから１６日夜遅くまで、東部では１６日昼過ぎから、強風に注意してください。",
      "observedAt": "2026-02-15T22:23:40.000Z",
      "placeCountry": "日本",
      "placePref": "高知県",
      "placeCity": null,
      "latitude": 33.6569018,
      "longitude": 133.5606241
    },
    {
      "originId": "https://www.data.jma.go.jp/developer/xml/data/20260215215536_0_VPWW53_460100.xml",
      "title": "気象特別警報・警報・注意報",
      "content": "【鹿児島県（奄美地方を除く）気象警報・注意報】薩摩地方では、１６日昼前まで濃霧による視程障害に注意してください。",
      "observedAt": "2026-02-15T21:55:36.000Z",
      "placeCountry": "日本",
      "placePref": "鹿児島県",
      "placeCity": null,
      "latitude": 31.521587,
      "longitude": 130.5474077
    },
    {
      "originId": "https://www.data.jma.go.jp/developer/xml/data/20260215214919_0_VPWW53_240000.xml",
      "title": "気象特別警報・警報・注意報",
      "content": "【三重県気象警報・注意報】北中部では１６日昼過ぎから１７日明け方まで、南部では１６日昼過ぎから１７日朝まで、強風に注意してください。",
      "observedAt": "2026-02-15T21:49:18.000Z",
      "placeCountry": "日本",
      "placePref": "三重県",
      "placeCity": null,
      "latitude": 34.7339685,
      "longitude": 136.5154489
    },
    {
      "originId": "https://www.data.jma.go.jp/developer/xml/data/20260215214211_0_VPWW53_230000.xml",
      "title": "気象特別警報・警報・注意報",
      "content": "【愛知県気象警報・注意報】西部では１６日昼過ぎから１７日明け方まで、東部では１６日昼過ぎから１７日朝まで、強風に注意してください。",
      "observedAt": "2026-02-15T21:42:11.000Z",
      "placeCountry": "日本",
      "placePref": "愛知県",
      "placeCity": null,
      "latitude": 34.9991645,
      "longitude": 137.254574
    },
    {
      "originId": "https://www.data.jma.go.jp/developer/xml/data/20260215214113_0_VPWW53_220000.xml",
      "title": "気象特別警報・警報・注意報",
      "content": "【静岡県気象警報・注意報】中部、西部では、１６日昼過ぎから１７日明け方まで強風に注意してください。",
      "observedAt": "2026-02-15T21:41:13.000Z",
      "placeCountry": "日本",
      "placePref": "静岡県",
      "placeCity": null,
      "latitude": 34.9332488,
      "longitude": 138.0955398
    },
    {
      "originId": "https://www.data.jma.go.jp/developer/xml/data/20260215213814_0_VPWW53_130000.xml",
      "title": "気象特別警報・警報・注意報",
      "content": "【東京都気象警報・注意報】東京地方では、１６日まで空気の乾燥した状態が続くため、火の取り扱いに注意してください。",
      "observedAt": "2026-02-15T21:38:13.000Z",
      "placeCountry": "日本",
      "placePref": "東京都",
      "placeCity": null,
      "latitude": 35.6828387,
      "longitude": 139.7594549
    },
    {
      "originId": "https://www.data.jma.go.jp/developer/xml/data/20260215213619_0_VPWW53_420000.xml",
      "title": "気象特別警報・警報・注意報",
      "content": "【長崎県気象警報・注意報】五島では１６日昼前まで、壱岐・対馬では１６日夜遅くまで、南部、北部では１７日明け方まで、強風に注意してください。南部、北部では、１６日昼前まで濃霧による視程障害に注意してください。",
      "observedAt": "2026-02-15T21:36:18.000Z",
      "placeCountry": "日本",
      "placePref": "長崎県",
      "placeCity": null,
      "latitude": 33.1154683,
      "longitude": 129.7874339
    },
    {
      "originId": "https://www.data.jma.go.jp/developer/xml/data/20260215212915_0_VPWW53_120000.xml",
      "title": "気象特別警報・警報・注意報",
      "content": "【千葉県気象警報・注意報】北東部、南部では、１６日昼過ぎから高波に注意してください。千葉県では、１６日昼前まで濃霧による視程障害に注意してください。",
      "observedAt": "2026-02-15T21:29:15.000Z",
      "placeCountry": "日本",
      "placePref": "千葉県",
      "placeCity": null,
      "latitude": 35.549399,
      "longitude": 140.2647303
    },
    {
      "originId": "https://www.data.jma.go.jp/developer/xml/data/20260215212812_0_VPWW53_080000.xml",
      "title": "気象特別警報・警報・注意報",
      "content": "【茨城県気象警報・注意報】南部では、１６日昼過ぎから高波に注意してください。茨城県では、１６日昼前まで濃霧による視程障害に注意してください。",
      "observedAt": "2026-02-15T21:28:11.000Z",
      "placeCountry": "日本",
      "placePref": "茨城県",
      "placeCity": null,
      "latitude": 36.2869536,
      "longitude": 140.4703384
    },
    {
      "originId": "https://www.data.jma.go.jp/developer/xml/data/20260215211411_0_VPWW53_160000.xml",
      "title": "気象特別警報・警報・注意報",
      "content": "【富山県気象警報・注意報】東部では、１６日昼過ぎから１６日夜遅くまで高波に注意してください。",
      "observedAt": "2026-02-15T21:14:10.000Z",
      "placeCountry": "日本",
      "placePref": "富山県",
      "placeCity": null,
      "latitude": 36.6468015,
      "longitude": 137.2183531
    },
    {
      "originId": "https://www.data.jma.go.jp/developer/xml/data/20260215210941_0_VPWW53_400000.xml",
      "title": "気象特別警報・警報・注意報",
      "content": "【福岡県気象警報・注意報】福岡、北九州地方では、１６日夜遅くまで強風に、１６日昼過ぎから１７日朝まで高波に注意してください。福岡県では、１６日昼前まで濃霧による視程障害に注意してください。",
      "observedAt": "2026-02-15T21:09:41.000Z",
      "placeCountry": "日本",
      "placePref": "福岡県",
      "placeCity": null,
      "latitude": 33.6251241,
      "longitude": 130.6180016
    },
    {
      "originId": "https://www.data.jma.go.jp/developer/xml/data/20260215210932_0_VPWW53_350000.xml",
      "title": "気象特別警報・警報・注意報",
      "content": "【山口県気象警報・注意報】山口県では、強風や濃霧による視程障害に注意してください。西部、東部、北部では、高波に注意してください。",
      "observedAt": "2026-02-15T21:09:32.000Z",
      "placeCountry": "日本",
      "placePref": "山口県",
      "placeCity": null,
      "latitude": 34.2379614,
      "longitude": 131.5873845
    },
    {
      "originId": "https://www.data.jma.go.jp/developer/xml/data/20260215193518_0_VPWW53_250000.xml",
      "title": "気象特別警報・警報・注意報",
      "content": "【滋賀県気象警報・注意報】滋賀県では、１６日昼前から１６日夜遅くまで強風に注意してください。北部では、１６日までなだれに注意してください。",
      "observedAt": "2026-02-15T19:35:17.000Z",
      "placeCountry": "日本",
      "placePref": "滋賀県",
      "placeCity": null,
      "latitude": 35.247154,
      "longitude": 136.109385
    },
    {
      "originId": "https://www.data.jma.go.jp/developer/xml/data/20260215193504_0_VPWW53_260000.xml",
      "title": "気象特別警報・警報・注意報",
      "content": "【京都府気象警報・注意報】京都府では、１６日昼前まで濃霧による視程障害に注意してください。北部では、１７日までなだれに注意してください。",
      "observedAt": "2026-02-15T19:35:04.000Z",
      "placeCountry": "日本",
      "placePref": "京都府",
      "placeCity": null,
      "latitude": 35.242552,
      "longitude": 135.454601
    },
    {
      "originId": "https://www.data.jma.go.jp/developer/xml/data/20260215192956_0_VPWW53_410000.xml",
      "title": "気象特別警報・警報・注意報",
      "content": "【佐賀県気象警報・注意報】北部では、１７日明け方まで強風に注意してください。佐賀県では、１６日昼前まで濃霧による視程障害に注意してください。",
      "observedAt": "2026-02-15T19:29:56.000Z",
      "placeCountry": "日本",
      "placePref": "佐賀県",
      "placeCity": null,
      "latitude": 33.2185408,
      "longitude": 130.1296585
    },
    {
      "originId": "https://www.data.jma.go.jp/developer/xml/data/20260215192953_0_VPWW53_420000.xml",
      "title": "気象特別警報・警報・注意報",
      "content": "【長崎県気象警報・注意報】五島では１６日昼前まで、壱岐・対馬では１６日夜遅くまで、南部、北部では１７日明け方まで、強風に注意してください。",
      "observedAt": "2026-02-15T19:29:52.000Z",
      "placeCountry": "日本",
      "placePref": "長崎県",
      "placeCity": null,
      "latitude": 33.1154683,
      "longitude": 129.7874339
    },
    {
      "originId": "https://www.data.jma.go.jp/developer/xml/data/20260215192907_0_VPWW53_300000.xml",
      "title": "気象特別警報・警報・注意報",
      "content": "【和歌山県気象警報・注意報】和歌山県では、１６日昼前から１７日明け方まで強風に注意してください。",
      "observedAt": "2026-02-15T19:29:07.000Z",
      "placeCountry": "日本",
      "placePref": "和歌山県",
      "placeCity": null,
      "latitude": 33.8070292,
      "longitude": 135.5930743
    },
    {
      "originId": "https://www.data.jma.go.jp/developer/xml/data/20260215192008_0_VPWW53_360000.xml",
      "title": "気象特別警報・警報・注意報",
      "content": "【徳島県気象警報・注意報】南部では１６日朝から、北部では１６日昼過ぎから１６日夜遅くまで、強風に注意してください。",
      "observedAt": "2026-02-15T19:20:07.000Z",
      "placeCountry": "日本",
      "placePref": "徳島県",
      "placeCity": null,
      "latitude": 33.9196418,
      "longitude": 134.2509634
    },
    {
      "originId": "https://www.data.jma.go.jp/developer/xml/data/20260215191827_0_VPWW53_280000.xml",
      "title": "気象特別警報・警報・注意報",
      "content": "【兵庫県気象警報・注意報】兵庫県では、１６日昼前まで濃霧による視程障害に、１７日までなだれに注意してください。",
      "observedAt": "2026-02-15T19:18:27.000Z",
      "placeCountry": "日本",
      "placePref": "兵庫県",
      "placeCity": null,
      "latitude": 34.914934,
      "longitude": 134.860666
    },
    {
      "originId": "https://www.data.jma.go.jp/developer/xml/data/20260215191031_0_VPWW53_110000.xml",
      "title": "気象特別警報・警報・注意報",
      "content": "【埼玉県気象警報・注意報】南部、北部では、１６日まで空気の乾燥した状態が続くため、火の取り扱いに注意してください。",
      "observedAt": "2026-02-15T19:10:31.000Z",
      "placeCountry": "日本",
      "placePref": "埼玉県",
      "placeCity": null,
      "latitude": 35.9754168,
      "longitude": 139.4160114
    },
    {
      "originId": "https://www.data.jma.go.jp/developer/xml/data/20260215190924_0_VPWW53_350000.xml",
      "title": "気象特別警報・警報・注意報",
      "content": "【山口県気象警報・注意報】西部、北部では、１６日夜遅くまで強風に注意してください。山口県では、１６日昼前まで濃霧による視程障害に注意してください。",
      "observedAt": "2026-02-15T19:09:23.000Z",
      "placeCountry": "日本",
      "placePref": "山口県",
      "placeCity": null,
      "latitude": 34.2379614,
      "longitude": 131.5873845
    },
    {
      "originId": "https://www.data.jma.go.jp/developer/xml/data/20260215190823_0_VPWW53_150000.xml",
      "title": "気象特別警報・警報・注意報",
      "content": "【新潟県気象警報・注意報】下越、佐渡では、１６日朝から１６日夜遅くまで高波に注意してください。下越、中越、上越では、１６日昼前まで濃霧による視程障害に注意してください。",
      "observedAt": "2026-02-15T19:08:22.000Z",
      "placeCountry": "日本",
      "placePref": "新潟県",
      "placeCity": null,
      "latitude": 37.6452283,
      "longitude": 138.7669125
    },
    {
      "originId": "https://www.data.jma.go.jp/developer/xml/data/20260215190811_0_VPWW53_100000.xml",
      "title": "気象特別警報・警報・注意報",
      "content": "【群馬県気象警報・注意報】群馬県では、１８日まで空気の乾燥した状態が続くため、火の取り扱いに注意してください。",
      "observedAt": "2026-02-15T19:08:10.000Z",
      "placeCountry": "日本",
      "placePref": "群馬県",
      "placeCity": null,
      "latitude": 36.52198,
      "longitude": 139.033483
    }
  ]
}