{
  "generatedAt": "2025-10-01T10:08:29.587Z",
  "timeZone": "Asia/Tokyo",
  "hourPath": "2025/10/01/19",
  "source": "http://www.data.jma.go.jp/developer/xml/feed/extra.xml",
  "totalItems": 81,
  "items": [
    {
      "originId": "https://www.data.jma.go.jp/developer/xml/data/20251001100041_0_VPWW53_270000.xml",
      "title": "気象特別警報・警報・注意報",
      "content": "【大阪府気象警報・注意報】注意報を解除します。",
      "observedAt": "2025-10-01T10:00:40.000Z",
      "placeCountry": "日本",
      "placePref": "大阪府",
      "placeCity": null,
      "latitude": 34.6198813,
      "longitude": 135.490357
    },
    {
      "originId": "https://www.data.jma.go.jp/developer/xml/data/20251001100039_0_VPWW53_280000.xml",
      "title": "気象特別警報・警報・注意報",
      "content": "【兵庫県気象警報・注意報】注意報を解除します。",
      "observedAt": "2025-10-01T10:00:38.000Z",
      "placeCountry": "日本",
      "placePref": "兵庫県",
      "placeCity": null,
      "latitude": 34.914934,
      "longitude": 134.860666
    },
    {
      "originId": "https://www.data.jma.go.jp/developer/xml/data/20251001095737_0_VPWW53_200000.xml",
      "title": "気象特別警報・警報・注意報",
      "content": "【長野県気象警報・注意報】中部では、１日夜のはじめ頃まで低い土地の浸水や河川の増水に注意してください。中部、南部では１日夜のはじめ頃まで、北部では２日明け方まで、落雷に注意してください。",
      "observedAt": "2025-10-01T09:57:36.000Z",
      "placeCountry": "日本",
      "placePref": "長野県",
      "placeCity": null,
      "latitude": 36.1143945,
      "longitude": 138.0319015
    },
    {
      "originId": "https://www.data.jma.go.jp/developer/xml/data/20251001092721_0_VPWW53_150000.xml",
      "title": "気象特別警報・警報・注意報",
      "content": "【新潟県気象警報・注意報】上越では、土砂災害に注意してください。下越、中越、上越では、低い土地の浸水に注意してください。新潟県では、竜巻などの激しい突風や落雷に注意してください。",
      "observedAt": "2025-10-01T09:27:20.000Z",
      "placeCountry": "日本",
      "placePref": "新潟県",
      "placeCity": null,
      "latitude": 37.6452283,
      "longitude": 138.7669125
    },
    {
      "originId": "https://www.data.jma.go.jp/developer/xml/data/20251001092413_0_VPWW53_080000.xml",
      "title": "気象特別警報・警報・注意報",
      "content": "【茨城県気象警報・注意報】茨城県では、１日夜遅くまで急な強い雨や落雷に、２日未明から２日昼前まで濃霧による視程障害に注意してください。",
      "observedAt": "2025-10-01T09:24:12.000Z",
      "placeCountry": "日本",
      "placePref": "茨城県",
      "placeCity": null,
      "latitude": 36.2869536,
      "longitude": 140.4703384
    },
    {
      "originId": "https://www.data.jma.go.jp/developer/xml/data/20251001091822_0_VPWW53_040000.xml",
      "title": "気象特別警報・警報・注意報",
      "content": "【宮城県気象警報・注意報】東部では、２日明け方まで土砂災害に注意してください。宮城県では、２日明け方まで竜巻などの激しい突風や落雷に注意してください。",
      "observedAt": "2025-10-01T09:18:22.000Z",
      "placeCountry": "日本",
      "placePref": "宮城県",
      "placeCity": null,
      "latitude": 38.3880155,
      "longitude": 140.9761025
    },
    {
      "originId": "https://www.data.jma.go.jp/developer/xml/data/20251001091808_0_VPWW53_060000.xml",
      "title": "気象特別警報・警報・注意報",
      "content": "【山形県気象警報・注意報】村山、置賜では、土砂災害や河川の増水に注意してください。置賜、庄内では、低い土地の浸水に注意してください。山形県では、竜巻などの激しい突風や落雷に注意してください。",
      "observedAt": "2025-10-01T09:18:07.000Z",
      "placeCountry": "日本",
      "placePref": "山形県",
      "placeCity": null,
      "latitude": 38.4746705,
      "longitude": 140.083237
    },
    {
      "originId": "https://www.data.jma.go.jp/developer/xml/data/20251001085534_0_VPWW53_250000.xml",
      "title": "気象特別警報・警報・注意報",
      "content": "【滋賀県気象警報・注意報】注意報を解除します。",
      "observedAt": "2025-10-01T08:55:33.000Z",
      "placeCountry": "日本",
      "placePref": "滋賀県",
      "placeCity": null,
      "latitude": 35.247154,
      "longitude": 136.109385
    },
    {
      "originId": "https://www.data.jma.go.jp/developer/xml/data/20251001085533_0_VPWW53_260000.xml",
      "title": "気象特別警報・警報・注意報",
      "content": "【京都府気象警報・注意報】注意報を解除します。",
      "observedAt": "2025-10-01T08:55:32.000Z",
      "placeCountry": "日本",
      "placePref": "京都府",
      "placeCity": null,
      "latitude": 35.242552,
      "longitude": 135.454601
    },
    {
      "originId": "https://www.data.jma.go.jp/developer/xml/data/20251001085318_0_VPWW53_170000.xml",
      "title": "気象特別警報・警報・注意報",
      "content": "【石川県気象警報・注意報】能登では、１日夜のはじめ頃から２日昼過ぎまで高潮に注意してください。石川県では、２日明け方まで竜巻などの激しい突風や急な強い雨、落雷に注意してください。",
      "observedAt": "2025-10-01T08:53:17.000Z",
      "placeCountry": "日本",
      "placePref": "石川県",
      "placeCity": null,
      "latitude": 36.9888678,
      "longitude": 136.8163563
    },
    {
      "originId": "https://www.data.jma.go.jp/developer/xml/data/20251001084717_0_VPWW53_120000.xml",
      "title": "気象特別警報・警報・注意報",
      "content": "【千葉県気象警報・注意報】千葉県では、１日夜遅くまで竜巻などの激しい突風や急な強い雨、落雷に、２日未明から２日昼前まで濃霧による視程障害に注意してください。",
      "observedAt": "2025-10-01T08:47:16.000Z",
      "placeCountry": "日本",
      "placePref": "千葉県",
      "placeCity": null,
      "latitude": 35.549399,
      "longitude": 140.2647303
    },
    {
      "originId": "https://www.data.jma.go.jp/developer/xml/data/20251001084212_0_VPWW53_230000.xml",
      "title": "気象特別警報・警報・注意報",
      "content": "【愛知県気象警報・注意報】注意報を解除します。",
      "observedAt": "2025-10-01T08:42:11.000Z",
      "placeCountry": "日本",
      "placePref": "愛知県",
      "placeCity": null,
      "latitude": 34.9991645,
      "longitude": 137.254574
    },
    {
      "originId": "https://www.data.jma.go.jp/developer/xml/data/20251001083912_0_VPWW53_200000.xml",
      "title": "気象特別警報・警報・注意報",
      "content": "【長野県気象警報・注意報】北部、中部では、１日夜のはじめ頃まで低い土地の浸水や河川の増水に注意してください。北部では２日明け方まで、中部、南部では１日夜のはじめ頃まで、落雷に注意してください。",
      "observedAt": "2025-10-01T08:39:11.000Z",
      "placeCountry": "日本",
      "placePref": "長野県",
      "placeCity": null,
      "latitude": 36.1143945,
      "longitude": 138.0319015
    },
    {
      "originId": "https://www.data.jma.go.jp/developer/xml/data/20251001083034_0_VPWW53_070000.xml",
      "title": "気象特別警報・警報・注意報",
      "content": "【福島県気象警報・注意報】会津では、１日夜遅くまで土砂災害に注意してください。福島県では、２日明け方まで竜巻などの激しい突風や落雷に注意してください。",
      "observedAt": "2025-10-01T08:30:33.000Z",
      "placeCountry": "日本",
      "placePref": "福島県",
      "placeCity": null,
      "latitude": 37.3662591,
      "longitude": 140.2511854
    },
    {
      "originId": "https://www.data.jma.go.jp/developer/xml/data/20251001082339_0_VPWW53_200000.xml",
      "title": "気象特別警報・警報・注意報",
      "content": "【長野県気象警報・注意報】北部、中部では、１日夜のはじめ頃まで低い土地の浸水や河川の増水に注意してください。北部では２日明け方まで、中部、南部では１日夜のはじめ頃まで、落雷に注意してください。",
      "observedAt": "2025-10-01T08:23:39.000Z",
      "placeCountry": "日本",
      "placePref": "長野県",
      "placeCity": null,
      "latitude": 36.1143945,
      "longitude": 138.0319015
    },
    {
      "originId": "https://www.data.jma.go.jp/developer/xml/data/20251001081420_0_VPWW53_060000.xml",
      "title": "気象特別警報・警報・注意報",
      "content": "【山形県気象警報・注意報】置賜では、１日夜遅くまで河川の増水に警戒してください。",
      "observedAt": "2025-10-01T08:14:19.000Z",
      "placeCountry": "日本",
      "placePref": "山形県",
      "placeCity": null,
      "latitude": 38.4746705,
      "longitude": 140.083237
    },
    {
      "originId": "https://www.data.jma.go.jp/developer/xml/data/20251001075114_0_VPWW53_060000.xml",
      "title": "気象特別警報・警報・注意報",
      "content": "【山形県気象警報・注意報】置賜では、１日夜遅くまで河川の増水に警戒してください。",
      "observedAt": "2025-10-01T07:51:13.000Z",
      "placeCountry": "日本",
      "placePref": "山形県",
      "placeCity": null,
      "latitude": 38.4746705,
      "longitude": 140.083237
    },
    {
      "originId": "https://www.data.jma.go.jp/developer/xml/data/20251001074317_0_VPWW53_140000.xml",
      "title": "気象特別警報・警報・注意報",
      "content": "【神奈川県気象警報・注意報】神奈川県では、１日夜遅くまで竜巻などの激しい突風や急な強い雨、落雷に注意してください。",
      "observedAt": "2025-10-01T07:43:16.000Z",
      "placeCountry": "日本",
      "placePref": "神奈川県",
      "placeCity": null,
      "latitude": 35.4342935,
      "longitude": 139.374753
    },
    {
      "originId": "https://www.data.jma.go.jp/developer/xml/data/20251001073039_0_VPWW53_200000.xml",
      "title": "気象特別警報・警報・注意報",
      "content": "【長野県気象警報・注意報】北部、中部では、１日夜のはじめ頃まで低い土地の浸水や河川の増水に注意してください。北部では２日明け方まで、中部、南部では１日夜のはじめ頃まで、落雷に注意してください。",
      "observedAt": "2025-10-01T07:30:38.000Z",
      "placeCountry": "日本",
      "placePref": "長野県",
      "placeCity": null,
      "latitude": 36.1143945,
      "longitude": 138.0319015
    },
    {
      "originId": "https://www.data.jma.go.jp/developer/xml/data/20251001072615_0_VPWW53_100000.xml",
      "title": "気象特別警報・警報・注意報",
      "content": "【群馬県気象警報・注意報】群馬県では、１日夜のはじめ頃まで急な強い雨や落雷に、２日昼前まで濃霧による視程障害に注意してください。",
      "observedAt": "2025-10-01T07:26:15.000Z",
      "placeCountry": "日本",
      "placePref": "群馬県",
      "placeCity": null,
      "latitude": 36.52198,
      "longitude": 139.033483
    },
    {
      "originId": "https://www.data.jma.go.jp/developer/xml/data/20251001072254_0_VPWW53_150000.xml",
      "title": "気象特別警報・警報・注意報",
      "content": "【新潟県気象警報・注意報】新潟県では、１日夜のはじめ頃まで低い土地の浸水に、２日朝まで竜巻などの激しい突風や落雷に注意してください。佐渡では、１日夜のはじめ頃まで河川の増水に注意してください。",
      "observedAt": "2025-10-01T07:22:53.000Z",
      "placeCountry": "日本",
      "placePref": "新潟県",
      "placeCity": null,
      "latitude": 37.6452283,
      "longitude": 138.7669125
    },
    {
      "originId": "https://www.data.jma.go.jp/developer/xml/data/20251001071912_0_VPWW53_110000.xml",
      "title": "気象特別警報・警報・注意報",
      "content": "【埼玉県気象警報・注意報】埼玉県では、１日夜遅くまで急な強い雨や落雷に、２日未明から２日昼前まで濃霧による視程障害に注意してください。",
      "observedAt": "2025-10-01T07:19:11.000Z",
      "placeCountry": "日本",
      "placePref": "埼玉県",
      "placeCity": null,
      "latitude": 35.9754168,
      "longitude": 139.4160114
    },
    {
      "originId": "https://www.data.jma.go.jp/developer/xml/data/20251001071710_0_VPWW53_210000.xml",
      "title": "気象特別警報・警報・注意報",
      "content": "【岐阜県気象警報・注意報】注意報を解除します。",
      "observedAt": "2025-10-01T07:17:09.000Z",
      "placeCountry": "日本",
      "placePref": "岐阜県",
      "placeCity": null,
      "latitude": 35.7867449,
      "longitude": 137.0460777
    },
    {
      "originId": "https://www.data.jma.go.jp/developer/xml/data/20251001071118_0_VPWW53_200000.xml",
      "title": "気象特別警報・警報・注意報",
      "content": "【長野県気象警報・注意報】北部、中部では、低い土地の浸水に注意してください。北部では、河川の増水に注意してください。長野県では、落雷に注意してください。",
      "observedAt": "2025-10-01T07:11:18.000Z",
      "placeCountry": "日本",
      "placePref": "長野県",
      "placeCity": null,
      "latitude": 36.1143945,
      "longitude": 138.0319015
    },
    {
      "originId": "https://www.data.jma.go.jp/developer/xml/data/20251001071031_0_VPWW53_130000.xml",
      "title": "気象特別警報・警報・注意報",
      "content": "【東京都気象警報・注意報】伊豆諸島北部では、高波に注意してください。東京都では、竜巻などの激しい突風や急な強い雨、落雷に注意してください。東京地方では、濃霧による視程障害に注意してください。",
      "observedAt": "2025-10-01T07:10:29.000Z",
      "placeCountry": "日本",
      "placePref": "東京都",
      "placeCity": null,
      "latitude": 35.6828387,
      "longitude": 139.7594549
    },
    {
      "originId": "https://www.data.jma.go.jp/developer/xml/data/20251001070930_0_VPWW53_240000.xml",
      "title": "気象特別警報・警報・注意報",
      "content": "【三重県気象警報・注意報】三重県では、１日夜遅くまで急な強い雨や落雷に注意してください。",
      "observedAt": "2025-10-01T07:09:30.000Z",
      "placeCountry": "日本",
      "placePref": "三重県",
      "placeCity": null,
      "latitude": 34.7339685,
      "longitude": 136.5154489
    },
    {
      "originId": "https://www.data.jma.go.jp/developer/xml/data/20251001070819_0_VPWW53_180000.xml",
      "title": "気象特別警報・警報・注意報",
      "content": "【福井県気象警報・注意報】注意報を解除します。",
      "observedAt": "2025-10-01T07:08:19.000Z",
      "placeCountry": "日本",
      "placePref": "福井県",
      "placeCity": null,
      "latitude": 35.9263502,
      "longitude": 136.6068127
    },
    {
      "originId": "https://www.data.jma.go.jp/developer/xml/data/20251001070706_0_VPWW53_060000.xml",
      "title": "気象特別警報・警報・注意報",
      "content": "【山形県気象警報・注意報】置賜では、１日夜遅くまで河川の増水に警戒してください。",
      "observedAt": "2025-10-01T07:07:05.000Z",
      "placeCountry": "日本",
      "placePref": "山形県",
      "placeCity": null,
      "latitude": 38.4746705,
      "longitude": 140.083237
    },
    {
      "originId": "https://www.data.jma.go.jp/developer/xml/data/20251001070649_0_VPWW53_090000.xml",
      "title": "気象特別警報・警報・注意報",
      "content": "【栃木県気象警報・注意報】栃木県では、１日夜のはじめ頃まで急な強い雨や落雷に、２日昼前まで濃霧による視程障害に注意してください。",
      "observedAt": "2025-10-01T07:06:48.000Z",
      "placeCountry": "日本",
      "placePref": "栃木県",
      "placeCity": null,
      "latitude": 36.6782167,
      "longitude": 139.8096549
    },
    {
      "originId": "https://www.data.jma.go.jp/developer/xml/data/20251001065843_0_VPWW53_120000.xml",
      "title": "気象特別警報・警報・注意報",
      "content": "【千葉県気象警報・注意報】北西部、北東部では、低い土地の浸水や河川の増水に注意してください。千葉県では、竜巻などの激しい突風や落雷、濃霧による視程障害に注意してください。",
      "observedAt": "2025-10-01T06:58:42.000Z",
      "placeCountry": "日本",
      "placePref": "千葉県",
      "placeCity": null,
      "latitude": 35.549399,
      "longitude": 140.2647303
    },
    {
      "originId": "https://www.data.jma.go.jp/developer/xml/data/20251001065806_0_VPWW53_040000.xml",
      "title": "気象特別警報・警報・注意報",
      "content": "【宮城県気象警報・注意報】東部では、１日夜遅くまで土砂災害に警戒してください。",
      "observedAt": "2025-10-01T06:58:05.000Z",
      "placeCountry": "日本",
      "placePref": "宮城県",
      "placeCity": null,
      "latitude": 38.3880155,
      "longitude": 140.9761025
    },
    {
      "originId": "https://www.data.jma.go.jp/developer/xml/data/20251001065316_0_VPWW53_080000.xml",
      "title": "気象特別警報・警報・注意報",
      "content": "【茨城県気象警報・注意報】南部では、１日夜のはじめ頃まで低い土地の浸水や河川の増水に注意してください。茨城県では、１日夜遅くまで落雷に、２日未明から２日昼前まで濃霧による視程障害に注意してください。",
      "observedAt": "2025-10-01T06:53:15.000Z",
      "placeCountry": "日本",
      "placePref": "茨城県",
      "placeCity": null,
      "latitude": 36.2869536,
      "longitude": 140.4703384
    },
    {
      "originId": "https://www.data.jma.go.jp/developer/xml/data/20251001065127_0_VPWW53_460100.xml",
      "title": "気象特別警報・警報・注意報",
      "content": "【鹿児島県（奄美地方を除く）気象警報・注意報】種子島・屋久島地方では、１日夜遅くまで急な強い雨や落雷に注意してください。",
      "observedAt": "2025-10-01T06:51:26.000Z",
      "placeCountry": "日本",
      "placePref": "鹿児島県",
      "placeCity": null,
      "latitude": 31.521587,
      "longitude": 130.5474077
    },
    {
      "originId": "https://www.data.jma.go.jp/developer/xml/data/20251001065008_0_VPWW53_460040.xml",
      "title": "気象特別警報・警報・注意報",
      "content": "【奄美地方（鹿児島県）気象警報・注意報】奄美地方では、急な強い雨や落雷に注意してください。",
      "observedAt": "2025-10-01T06:50:08.000Z",
      "placeCountry": "日本",
      "placePref": "鹿児島県",
      "placeCity": null,
      "latitude": 31.521587,
      "longitude": 130.5474077
    },
    {
      "originId": "https://www.data.jma.go.jp/developer/xml/data/20251001065004_0_VPWW53_170000.xml",
      "title": "気象特別警報・警報・注意報",
      "content": "【石川県気象警報・注意報】能登では、１日夜遅くまで土砂災害や河川の増水に、１日夜のはじめ頃から２日昼過ぎまで高潮に注意してください。石川県では、２日明け方まで竜巻などの激しい突風や落雷に注意してください。",
      "observedAt": "2025-10-01T06:50:03.000Z",
      "placeCountry": "日本",
      "placePref": "石川県",
      "placeCity": null,
      "latitude": 36.9888678,
      "longitude": 136.8163563
    },
    {
      "originId": "https://www.data.jma.go.jp/developer/xml/data/20251001064426_0_VPWW53_120000.xml",
      "title": "気象特別警報・警報・注意報",
      "content": "【千葉県気象警報・注意報】北西部、北東部では、低い土地の浸水や河川の増水に注意してください。千葉県では、竜巻などの激しい突風や落雷、濃霧による視程障害に注意してください。",
      "observedAt": "2025-10-01T06:44:25.000Z",
      "placeCountry": "日本",
      "placePref": "千葉県",
      "placeCity": null,
      "latitude": 35.549399,
      "longitude": 140.2647303
    },
    {
      "originId": "https://www.data.jma.go.jp/developer/xml/data/20251001064421_0_VPWW53_060000.xml",
      "title": "気象特別警報・警報・注意報",
      "content": "【山形県気象警報・注意報】村山、置賜では土砂災害に、置賜では低い土地の浸水に、置賜、庄内では河川の増水に、山形県では竜巻などの激しい突風や落雷に注意してください。",
      "observedAt": "2025-10-01T06:44:20.000Z",
      "placeCountry": "日本",
      "placePref": "山形県",
      "placeCity": null,
      "latitude": 38.4746705,
      "longitude": 140.083237
    },
    {
      "originId": "https://www.data.jma.go.jp/developer/xml/data/20251001064234_0_VPWW53_070000.xml",
      "title": "気象特別警報・警報・注意報",
      "content": "【福島県気象警報・注意報】会津では、１日夜のはじめ頃まで土砂災害や低い土地の浸水、河川の増水に注意してください。福島県では、２日明け方まで竜巻などの激しい突風や落雷に注意してください。",
      "observedAt": "2025-10-01T06:42:34.000Z",
      "placeCountry": "日本",
      "placePref": "福島県",
      "placeCity": null,
      "latitude": 37.3662591,
      "longitude": 140.2511854
    },
    {
      "originId": "https://www.data.jma.go.jp/developer/xml/data/20251001064213_0_VPWW53_020000.xml",
      "title": "気象特別警報・警報・注意報",
      "content": "【青森県気象警報・注意報】青森県では、竜巻などの激しい突風や急な強い雨、落雷に注意してください。",
      "observedAt": "2025-10-01T06:42:13.000Z",
      "placeCountry": "日本",
      "placePref": "青森県",
      "placeCity": null,
      "latitude": 40.886943,
      "longitude": 140.590121
    },
    {
      "originId": "https://www.data.jma.go.jp/developer/xml/data/20251001063727_0_VPWW53_070000.xml",
      "title": "気象特別警報・警報・注意報",
      "content": "【福島県気象警報・注意報】会津では、１日夜のはじめ頃まで土砂災害や低い土地の浸水、河川の増水に注意してください。福島県では、２日明け方まで竜巻などの激しい突風や落雷に注意してください。",
      "observedAt": "2025-10-01T06:37:26.000Z",
      "placeCountry": "日本",
      "placePref": "福島県",
      "placeCity": null,
      "latitude": 37.3662591,
      "longitude": 140.2511854
    },
    {
      "originId": "https://www.data.jma.go.jp/developer/xml/data/20251001063042_0_VPWW53_280000.xml",
      "title": "気象特別警報・警報・注意報",
      "content": "【兵庫県気象警報・注意報】南部では、１日夜のはじめ頃まで急な強い雨や落雷に注意してください。",
      "observedAt": "2025-10-01T06:30:41.000Z",
      "placeCountry": "日本",
      "placePref": "兵庫県",
      "placeCity": null,
      "latitude": 34.914934,
      "longitude": 134.860666
    },
    {
      "originId": "https://www.data.jma.go.jp/developer/xml/data/20251001061509_0_VPWW53_060000.xml",
      "title": "気象特別警報・警報・注意報",
      "content": "【山形県気象警報・注意報】置賜では、低い土地の浸水に注意してください。庄内では、河川の増水に注意してください。山形県では、竜巻などの激しい突風や落雷に注意してください。",
      "observedAt": "2025-10-01T06:15:08.000Z",
      "placeCountry": "日本",
      "placePref": "山形県",
      "placeCity": null,
      "latitude": 38.4746705,
      "longitude": 140.083237
    },
    {
      "originId": "https://www.data.jma.go.jp/developer/xml/data/20251001053605_0_VPWW53_070000.xml",
      "title": "気象特別警報・警報・注意報",
      "content": "【福島県気象警報・注意報】会津では、土砂災害に注意してください。中通りでは、低い土地の浸水に注意してください。福島県では、竜巻などの激しい突風や落雷に注意してください。",
      "observedAt": "2025-10-01T05:36:05.000Z",
      "placeCountry": "日本",
      "placePref": "福島県",
      "placeCity": null,
      "latitude": 37.3662591,
      "longitude": 140.2511854
    },
    {
      "originId": "https://www.data.jma.go.jp/developer/xml/data/20251001052250_0_VPWW53_120000.xml",
      "title": "気象特別警報・警報・注意報",
      "content": "【千葉県気象警報・注意報】北西部、北東部では低い土地の浸水に、北西部では河川の増水に、南部では強風や高波に、千葉県では竜巻などの激しい突風や落雷に注意してください。",
      "observedAt": "2025-10-01T05:22:49.000Z",
      "placeCountry": "日本",
      "placePref": "千葉県",
      "placeCity": null,
      "latitude": 35.549399,
      "longitude": 140.2647303
    },
    {
      "originId": "https://www.data.jma.go.jp/developer/xml/data/20251001050920_0_VPWW53_120000.xml",
      "title": "気象特別警報・警報・注意報",
      "content": "【千葉県気象警報・注意報】北西部、北東部では、低い土地の浸水に注意してください。南部では、強風や高波に注意してください。千葉県では、竜巻などの激しい突風や落雷に注意してください。",
      "observedAt": "2025-10-01T05:09:19.000Z",
      "placeCountry": "日本",
      "placePref": "千葉県",
      "placeCity": null,
      "latitude": 35.549399,
      "longitude": 140.2647303
    },
    {
      "originId": "https://www.data.jma.go.jp/developer/xml/data/20251001044139_0_VPWW53_200000.xml",
      "title": "気象特別警報・警報・注意報",
      "content": "【長野県気象警報・注意報】北部では、１日夕方まで河川の増水に注意してください。長野県では、１日夜のはじめ頃まで落雷に注意してください。",
      "observedAt": "2025-10-01T04:41:38.000Z",
      "placeCountry": "日本",
      "placePref": "長野県",
      "placeCity": null,
      "latitude": 36.1143945,
      "longitude": 138.0319015
    },
    {
      "originId": "https://www.data.jma.go.jp/developer/xml/data/20251001043404_0_VPWW53_070000.xml",
      "title": "気象特別警報・警報・注意報",
      "content": "【福島県気象警報・注意報】中通り、浜通りでは、１日夕方まで低い土地の浸水に注意してください。福島県では、２日明け方まで竜巻などの激しい突風や落雷に注意してください。",
      "observedAt": "2025-10-01T04:34:03.000Z",
      "placeCountry": "日本",
      "placePref": "福島県",
      "placeCity": null,
      "latitude": 37.3662591,
      "longitude": 140.2511854
    },
    {
      "originId": "https://www.data.jma.go.jp/developer/xml/data/20251001043139_0_VPWW53_180000.xml",
      "title": "気象特別警報・警報・注意報",
      "content": "【福井県気象警報・注意報】嶺南では、１日夕方まで土砂災害に注意してください。福井県では、１日夕方まで落雷に注意してください。",
      "observedAt": "2025-10-01T04:31:39.000Z",
      "placeCountry": "日本",
      "placePref": "福井県",
      "placeCity": null,
      "latitude": 35.9263502,
      "longitude": 136.6068127
    },
    {
      "originId": "https://www.data.jma.go.jp/developer/xml/data/20251001042207_0_VPWW53_200000.xml",
      "title": "気象特別警報・警報・注意報",
      "content": "【長野県気象警報・注意報】北部では、１日夕方まで河川の増水に注意してください。長野県では、１日夜のはじめ頃まで落雷に注意してください。",
      "observedAt": "2025-10-01T04:22:06.000Z",
      "placeCountry": "日本",
      "placePref": "長野県",
      "placeCity": null,
      "latitude": 36.1143945,
      "longitude": 138.0319015
    },
    {
      "originId": "https://www.data.jma.go.jp/developer/xml/data/20251001040430_0_VPWW53_170000.xml",
      "title": "気象特別警報・警報・注意報",
      "content": "【石川県気象警報・注意報】能登では、１日夕方まで土砂災害に、２日昼過ぎまで高潮に注意してください。石川県では、１日夜遅くまで竜巻などの激しい突風や落雷に注意してください。",
      "observedAt": "2025-10-01T04:04:30.000Z",
      "placeCountry": "日本",
      "placePref": "石川県",
      "placeCity": null,
      "latitude": 36.9888678,
      "longitude": 136.8163563
    },
    {
      "originId": "https://www.data.jma.go.jp/developer/xml/data/20251001035434_0_VPWW53_040000.xml",
      "title": "気象特別警報・警報・注意報",
      "content": "【宮城県気象警報・注意報】東部では、１日夜遅くまで土砂災害や河川の増水に、１日夜のはじめ頃まで低い土地の浸水に警戒してください。",
      "observedAt": "2025-10-01T03:54:33.000Z",
      "placeCountry": "日本",
      "placePref": "宮城県",
      "placeCity": null,
      "latitude": 38.3880155,
      "longitude": 140.9761025
    },
    {
      "originId": "https://www.data.jma.go.jp/developer/xml/data/20251001033320_0_VPWW53_040000.xml",
      "title": "気象特別警報・警報・注意報",
      "content": "【宮城県気象警報・注意報】東部では、１日夜遅くまで土砂災害や河川の増水に、１日夜のはじめ頃まで低い土地の浸水に警戒してください。",
      "observedAt": "2025-10-01T03:33:19.000Z",
      "placeCountry": "日本",
      "placePref": "宮城県",
      "placeCity": null,
      "latitude": 38.3880155,
      "longitude": 140.9761025
    },
    {
      "originId": "https://www.data.jma.go.jp/developer/xml/data/20251001032137_0_VPWW53_070000.xml",
      "title": "気象特別警報・警報・注意報",
      "content": "【福島県気象警報・注意報】浜通りでは、１日夕方まで低い土地の浸水に注意してください。福島県では、２日明け方まで竜巻などの激しい突風や落雷に注意してください。",
      "observedAt": "2025-10-01T03:21:36.000Z",
      "placeCountry": "日本",
      "placePref": "福島県",
      "placeCity": null,
      "latitude": 37.3662591,
      "longitude": 140.2511854
    },
    {
      "originId": "https://www.data.jma.go.jp/developer/xml/data/20251001024704_0_VPWW53_040000.xml",
      "title": "気象特別警報・警報・注意報",
      "content": "【宮城県気象警報・注意報】東部では、１日夜遅くまで土砂災害や河川の増水に、１日夜のはじめ頃まで低い土地の浸水に警戒してください。",
      "observedAt": "2025-10-01T02:47:03.000Z",
      "placeCountry": "日本",
      "placePref": "宮城県",
      "placeCity": null,
      "latitude": 38.3880155,
      "longitude": 140.9761025
    },
    {
      "originId": "https://www.data.jma.go.jp/developer/xml/data/20251001023022_0_VPWW53_040000.xml",
      "title": "気象特別警報・警報・注意報",
      "content": "【宮城県気象警報・注意報】東部では、１日夜遅くまで土砂災害や河川の増水に、１日夜のはじめ頃まで低い土地の浸水に警戒してください。",
      "observedAt": "2025-10-01T02:30:21.000Z",
      "placeCountry": "日本",
      "placePref": "宮城県",
      "placeCity": null,
      "latitude": 38.3880155,
      "longitude": 140.9761025
    },
    {
      "originId": "https://www.data.jma.go.jp/developer/xml/data/20251001022311_0_VPWW53_150000.xml",
      "title": "気象特別警報・警報・注意報",
      "content": "【新潟県気象警報・注意報】新潟県では、１日夕方まで低い土地の浸水に、２日明け方まで竜巻などの激しい突風や落雷に注意してください。佐渡では、１日夜のはじめ頃まで河川の増水に注意してください。",
      "observedAt": "2025-10-01T02:23:11.000Z",
      "placeCountry": "日本",
      "placePref": "新潟県",
      "placeCity": null,
      "latitude": 37.6452283,
      "longitude": 138.7669125
    },
    {
      "originId": "https://www.data.jma.go.jp/developer/xml/data/20251001022039_0_VPWW53_180000.xml",
      "title": "気象特別警報・警報・注意報",
      "content": "【福井県気象警報・注意報】嶺南では、１日昼過ぎまで土砂災害に警戒してください。",
      "observedAt": "2025-10-01T02:20:39.000Z",
      "placeCountry": "日本",
      "placePref": "福井県",
      "placeCity": null,
      "latitude": 35.9263502,
      "longitude": 136.6068127
    },
    {
      "originId": "https://www.data.jma.go.jp/developer/xml/data/20251001015913_0_VPWW53_040000.xml",
      "title": "気象特別警報・警報・注意報",
      "content": "【宮城県気象警報・注意報】東部では、１日夜のはじめ頃まで低い土地の浸水に、１日夜遅くまで河川の増水に警戒してください。",
      "observedAt": "2025-10-01T01:59:12.000Z",
      "placeCountry": "日本",
      "placePref": "宮城県",
      "placeCity": null,
      "latitude": 38.3880155,
      "longitude": 140.9761025
    },
    {
      "originId": "https://www.data.jma.go.jp/developer/xml/data/20251001015816_0_VPWW53_150000.xml",
      "title": "気象特別警報・警報・注意報",
      "content": "【新潟県気象警報・注意報】新潟県では、１日夕方まで低い土地の浸水に、２日明け方まで竜巻などの激しい突風や落雷に注意してください。",
      "observedAt": "2025-10-01T01:58:16.000Z",
      "placeCountry": "日本",
      "placePref": "新潟県",
      "placeCity": null,
      "latitude": 37.6452283,
      "longitude": 138.7669125
    },
    {
      "originId": "https://www.data.jma.go.jp/developer/xml/data/20251001013507_0_VPWW53_040000.xml",
      "title": "気象特別警報・警報・注意報",
      "content": "【宮城県気象警報・注意報】東部では、１日夜のはじめ頃まで低い土地の浸水に、１日夜遅くまで河川の増水に警戒してください。",
      "observedAt": "2025-10-01T01:35:07.000Z",
      "placeCountry": "日本",
      "placePref": "宮城県",
      "placeCity": null,
      "latitude": 38.3880155,
      "longitude": 140.9761025
    },
    {
      "originId": "https://www.data.jma.go.jp/developer/xml/data/20251001011629_0_VPWW53_040000.xml",
      "title": "気象特別警報・警報・注意報",
      "content": "【宮城県気象警報・注意報】東部では、１日夜のはじめ頃まで低い土地の浸水に警戒してください。",
      "observedAt": "2025-10-01T01:16:28.000Z",
      "placeCountry": "日本",
      "placePref": "宮城県",
      "placeCity": null,
      "latitude": 38.3880155,
      "longitude": 140.9761025
    },
    {
      "originId": "https://www.data.jma.go.jp/developer/xml/data/20251001011217_0_VPWW53_310000.xml",
      "title": "気象特別警報・警報・注意報",
      "content": "【鳥取県気象警報・注意報】注意報を解除します。",
      "observedAt": "2025-10-01T01:12:16.000Z",
      "placeCountry": "日本",
      "placePref": "鳥取県",
      "placeCity": null,
      "latitude": 35.3555075,
      "longitude": 133.8678525
    },
    {
      "originId": "https://www.data.jma.go.jp/developer/xml/data/20251001010905_0_VPWW53_130000.xml",
      "title": "気象特別警報・警報・注意報",
      "content": "【東京都気象警報・注意報】伊豆諸島北部では、高波に注意してください。東京都では、竜巻などの激しい突風や急な強い雨、落雷に注意してください。",
      "observedAt": "2025-10-01T01:09:05.000Z",
      "placeCountry": "日本",
      "placePref": "東京都",
      "placeCity": null,
      "latitude": 35.6828387,
      "longitude": 139.7594549
    },
    {
      "originId": "https://www.data.jma.go.jp/developer/xml/data/20251001010745_0_VPWW53_100000.xml",
      "title": "気象特別警報・警報・注意報",
      "content": "【群馬県気象警報・注意報】群馬県では、１日夜のはじめ頃まで急な強い雨や落雷に、１日夕方まで濃霧による視程障害に注意してください。",
      "observedAt": "2025-10-01T01:07:44.000Z",
      "placeCountry": "日本",
      "placePref": "群馬県",
      "placeCity": null,
      "latitude": 36.52198,
      "longitude": 139.033483
    },
    {
      "originId": "https://www.data.jma.go.jp/developer/xml/data/20251001010648_0_VPWW53_040000.xml",
      "title": "気象特別警報・警報・注意報",
      "content": "【宮城県気象警報・注意報】東部では、１日夜のはじめ頃まで低い土地の浸水に警戒してください。",
      "observedAt": "2025-10-01T01:06:47.000Z",
      "placeCountry": "日本",
      "placePref": "宮城県",
      "placeCity": null,
      "latitude": 38.3880155,
      "longitude": 140.9761025
    },
    {
      "originId": "https://www.data.jma.go.jp/developer/xml/data/20251001010526_0_VPWW53_090000.xml",
      "title": "気象特別警報・警報・注意報",
      "content": "【栃木県気象警報・注意報】栃木県では、１日夜のはじめ頃まで急な強い雨や落雷に、１日夕方まで濃霧による視程障害に注意してください。",
      "observedAt": "2025-10-01T01:05:25.000Z",
      "placeCountry": "日本",
      "placePref": "栃木県",
      "placeCity": null,
      "latitude": 36.6782167,
      "longitude": 139.8096549
    },
    {
      "originId": "https://www.data.jma.go.jp/developer/xml/data/20251001010426_0_VPWW53_140000.xml",
      "title": "気象特別警報・警報・注意報",
      "content": "【神奈川県気象警報・注意報】東部では、１日夕方まで土砂災害に注意してください。神奈川県では、１日夜遅くまで竜巻などの激しい突風や落雷に注意してください。",
      "observedAt": "2025-10-01T01:04:26.000Z",
      "placeCountry": "日本",
      "placePref": "神奈川県",
      "placeCity": null,
      "latitude": 35.4342935,
      "longitude": 139.374753
    },
    {
      "originId": "https://www.data.jma.go.jp/developer/xml/data/20251001005806_0_VPWW53_070000.xml",
      "title": "気象特別警報・警報・注意報",
      "content": "【福島県気象警報・注意報】浜通りでは、１日夕方まで低い土地の浸水に警戒してください。",
      "observedAt": "2025-10-01T00:58:05.000Z",
      "placeCountry": "日本",
      "placePref": "福島県",
      "placeCity": null,
      "latitude": 37.3662591,
      "longitude": 140.2511854
    },
    {
      "originId": "https://www.data.jma.go.jp/developer/xml/data/20251001005115_0_VPWW53_290000.xml",
      "title": "気象特別警報・警報・注意報",
      "content": "【奈良県気象警報・注意報】奈良県では、１日昼過ぎから１日夜のはじめ頃まで急な強い雨や落雷に注意してください。",
      "observedAt": "2025-10-01T00:51:14.000Z",
      "placeCountry": "日本",
      "placePref": "奈良県",
      "placeCity": null,
      "latitude": 34.2963089,
      "longitude": 135.8816819
    },
    {
      "originId": "https://www.data.jma.go.jp/developer/xml/data/20251001004828_0_VPWW53_330000.xml",
      "title": "気象特別警報・警報・注意報",
      "content": "【岡山県気象警報・注意報】岡山県では、１日昼過ぎから１日夜のはじめ頃まで急な強い雨や落雷に注意してください。",
      "observedAt": "2025-10-01T00:48:27.000Z",
      "placeCountry": "日本",
      "placePref": "岡山県",
      "placeCity": null,
      "latitude": 34.8581334,
      "longitude": 133.7759256
    },
    {
      "originId": "https://www.data.jma.go.jp/developer/xml/data/20251001004827_0_VPWW53_340000.xml",
      "title": "気象特別警報・警報・注意報",
      "content": "【広島県気象警報・注意報】広島県では、１日昼過ぎから１日夜のはじめ頃まで急な強い雨や落雷に注意してください。南部では、１日まで空気の乾燥した状態が続くため、火の取り扱いに注意してください。",
      "observedAt": "2025-10-01T00:48:26.000Z",
      "placeCountry": "日本",
      "placePref": "広島県",
      "placeCity": null,
      "latitude": 34.5666725,
      "longitude": 132.753565
    },
    {
      "originId": "https://www.data.jma.go.jp/developer/xml/data/20251001004413_0_VPWW53_120000.xml",
      "title": "気象特別警報・警報・注意報",
      "content": "【千葉県気象警報・注意報】南部では、１日夕方まで強風や高波に注意してください。千葉県では、１日夜遅くまで竜巻などの激しい突風や急な強い雨、落雷に注意してください。",
      "observedAt": "2025-10-01T00:44:12.000Z",
      "placeCountry": "日本",
      "placePref": "千葉県",
      "placeCity": null,
      "latitude": 35.549399,
      "longitude": 140.2647303
    },
    {
      "originId": "https://www.data.jma.go.jp/developer/xml/data/20251001004224_0_VPWW53_070000.xml",
      "title": "気象特別警報・警報・注意報",
      "content": "【福島県気象警報・注意報】浜通りでは、１日夕方まで低い土地の浸水に注意してください。福島県では、２日明け方まで竜巻などの激しい突風や落雷に注意してください。",
      "observedAt": "2025-10-01T00:42:23.000Z",
      "placeCountry": "日本",
      "placePref": "福島県",
      "placeCity": null,
      "latitude": 37.3662591,
      "longitude": 140.2511854
    },
    {
      "originId": "https://www.data.jma.go.jp/developer/xml/data/20251001004208_0_VPWW53_030000.xml",
      "title": "気象特別警報・警報・注意報",
      "content": "【岩手県気象警報・注意報】岩手県では、２日明け方まで竜巻などの激しい突風や急な強い雨、落雷に注意してください。",
      "observedAt": "2025-10-01T00:42:07.000Z",
      "placeCountry": "日本",
      "placePref": "岩手県",
      "placeCity": null,
      "latitude": 39.5713763,
      "longitude": 141.4253574
    },
    {
      "originId": "https://www.data.jma.go.jp/developer/xml/data/20251001004051_0_VPWW53_180000.xml",
      "title": "気象特別警報・警報・注意報",
      "content": "【福井県気象警報・注意報】嶺南では、１日昼過ぎまで土砂災害に、１日昼前まで低い土地の浸水に警戒してください。",
      "observedAt": "2025-10-01T00:40:50.000Z",
      "placeCountry": "日本",
      "placePref": "福井県",
      "placeCity": null,
      "latitude": 35.9263502,
      "longitude": 136.6068127
    },
    {
      "originId": "https://www.data.jma.go.jp/developer/xml/data/20251001003852_0_VPWW53_050000.xml",
      "title": "気象特別警報・警報・注意報",
      "content": "【秋田県気象警報・注意報】秋田県では、竜巻などの激しい突風や急な強い雨、落雷に注意してください。",
      "observedAt": "2025-10-01T00:38:51.000Z",
      "placeCountry": "日本",
      "placePref": "秋田県",
      "placeCity": null,
      "latitude": 39.6898802,
      "longitude": 140.342608
    },
    {
      "originId": "https://www.data.jma.go.jp/developer/xml/data/20251001003634_0_VPWW53_040000.xml",
      "title": "気象特別警報・警報・注意報",
      "content": "【宮城県気象警報・注意報】東部では、１日夜のはじめ頃まで低い土地の浸水に警戒してください。",
      "observedAt": "2025-10-01T00:36:33.000Z",
      "placeCountry": "日本",
      "placePref": "宮城県",
      "placeCity": null,
      "latitude": 38.3880155,
      "longitude": 140.9761025
    },
    {
      "originId": "https://www.data.jma.go.jp/developer/xml/data/20251001001949_0_VPWW53_040000.xml",
      "title": "気象特別警報・警報・注意報",
      "content": "【宮城県気象警報・注意報】東部では、１日夜のはじめ頃まで低い土地の浸水に注意してください。宮城県では、２日明け方まで竜巻などの激しい突風や落雷に注意してください。",
      "observedAt": "2025-10-01T00:19:48.000Z",
      "placeCountry": "日本",
      "placePref": "宮城県",
      "placeCity": null,
      "latitude": 38.3880155,
      "longitude": 140.9761025
    },
    {
      "originId": "https://www.data.jma.go.jp/developer/xml/data/20251001001322_0_VPWW53_280000.xml",
      "title": "気象特別警報・警報・注意報",
      "content": "【兵庫県気象警報・注意報】北部では１日夕方まで、南部では１日夜のはじめ頃まで、急な強い雨や落雷に注意してください。",
      "observedAt": "2025-10-01T00:13:21.000Z",
      "placeCountry": "日本",
      "placePref": "兵庫県",
      "placeCity": null,
      "latitude": 34.914934,
      "longitude": 134.860666
    },
    {
      "originId": "https://www.data.jma.go.jp/developer/xml/data/20251001000748_0_VPWW53_170000.xml",
      "title": "気象特別警報・警報・注意報",
      "content": "【石川県気象警報・注意報】能登では、土砂災害や低い土地の浸水、河川の増水、高潮に注意してください。石川県では、竜巻などの激しい突風や落雷に注意してください。",
      "observedAt": "2025-10-01T00:07:47.000Z",
      "placeCountry": "日本",
      "placePref": "石川県",
      "placeCity": null,
      "latitude": 36.9888678,
      "longitude": 136.8163563
    },
    {
      "originId": "https://www.data.jma.go.jp/developer/xml/data/20251001000432_0_VPWW53_180000.xml",
      "title": "気象特別警報・警報・注意報",
      "content": "【福井県気象警報・注意報】福井県では、１日昼過ぎまで土砂災害に、１日夕方まで落雷に注意してください。嶺南では、１日昼前まで低い土地の浸水や河川の増水に注意してください。",
      "observedAt": "2025-10-01T00:04:31.000Z",
      "placeCountry": "日本",
      "placePref": "福井県",
      "placeCity": null,
      "latitude": 35.9263502,
      "longitude": 136.6068127
    }
  ]
}